{"place_id": 14493960, "licence": "Data \u00a9 OpenStreetMap contributors, ODbL 1.0. https://osm.org/copyright", "osm_type": "node", "osm_id": 1308628185, "lat": "1.1435966", "lon": "109.6747499", "display_name": "Gua, Sanggau Ledo, Bengkayang, Kalimantan Barat, Indonesia", "address": {"village": "Gua", "county": "Sanggau Ledo", "state_district": "Bengkayang", "state": "Kalimantan Barat", "country": "Indonesia", "country_code": "id"}, "boundingbox": ["1.1235966", "1.1635966", "109.6547499", "109.6947499"]}