{"place_id": 208341502, "licence": "Data \u00a9 OpenStreetMap contributors, ODbL 1.0. https://osm.org/copyright", "osm_type": "way", "osm_id": 579900537, "lat": "0.0626698", "lon": "111.5290055", "display_name": "Sungai Ana, Sintang, Kalimantan Barat, 78611, Indonesia", "address": {"village": "Sungai Ana", "county": "Sintang", "state_district": "Sintang", "state": "Kalimantan Barat", "postcode": "78611", "country": "Indonesia", "country_code": "id"}, "boundingbox": ["0.0626698", "0.0651924", "111.5260959", "111.5290055"]}