{"place_id": 204173778, "licence": "Data \u00a9 OpenStreetMap contributors, ODbL 1.0. https://osm.org/copyright", "osm_type": "way", "osm_id": 563781632, "lat": "-1.700188278292355", "lon": "110.79459625325461", "display_name": "Beringin Rayo, Tumbang Titi, Ketapang, Kalimantan Barat, Indonesia", "address": {"village": "Beringin Rayo", "county": "Tumbang Titi", "state_district": "Ketapang", "state": "Kalimantan Barat", "country": "Indonesia", "country_code": "id"}, "boundingbox": ["-1.739317", "-1.597309", "110.7422062", "110.8440578"]}