{"place_id": 14159185, "licence": "Data \u00a9 OpenStreetMap contributors, ODbL 1.0. https://osm.org/copyright", "osm_type": "node", "osm_id": 1308618985, "lat": "1.3015566", "lon": "109.5604788", "display_name": "Sepantai, Sejangkung, Sambas, Kalimantan Barat, Indonesia", "address": {"village": "Sepantai", "county": "Sejangkung", "state_district": "Sambas", "state": "Kalimantan Barat", "country": "Indonesia", "country_code": "id"}, "boundingbox": ["1.2815566", "1.3215566", "109.5404788", "109.5804788"]}