{"place_id": 14149535, "licence": "Data \u00a9 OpenStreetMap contributors, ODbL 1.0. https://osm.org/copyright", "osm_type": "node", "osm_id": 1308464859, "lat": "-2.6413964", "lon": "107.7763384", "display_name": "Air Selumar, Belitung, Kepulauan Bangka Belitung, Indonesia", "address": {"village": "Air Selumar", "state_district": "Belitung", "state": "Kepulauan Bangka Belitung", "country": "Indonesia", "country_code": "id"}, "boundingbox": ["-2.6613964", "-2.6213964", "107.7563384", "107.7963384"]}