{"place_id": 274571578, "licence": "Data \u00a9 OpenStreetMap contributors, ODbL 1.0. https://osm.org/copyright", "osm_type": "relation", "osm_id": 10621611, "lat": "0.8070994499999999", "lon": "109.0990076382474", "display_name": "Monterado, Bengkayang, Kalimantan Barat, Indonesia", "address": {"county": "Monterado", "state_district": "Bengkayang", "state": "Kalimantan Barat", "country": "Indonesia", "country_code": "id"}, "boundingbox": ["0.6515597", "0.9625561", "109.0246784", "109.2253202"]}