{"place_id": 14269063, "licence": "Data \u00a9 OpenStreetMap contributors, ODbL 1.0. https://osm.org/copyright", "osm_type": "node", "osm_id": 1308402016, "lat": "-0.2046473", "lon": "103.0346891", "display_name": "Teluk Sungka Hilir, Kecamatan Gaung Anak Serka, Kabupaten Indragiri Hilir, Riau, Indonesia", "address": {"village": "Teluk Sungka Hilir", "county": "Kecamatan Gaung Anak Serka", "state_district": "Kabupaten Indragiri Hilir", "state": "Riau", "country": "Indonesia", "country_code": "id"}, "boundingbox": ["-0.2246473", "-0.1846473", "103.0146891", "103.0546891"]}